{
  "$schema": "https://cdn.jsdelivr.net/gh/streetsidesoftware/cspell/cspell.schema.json",
  "dictionaries": [
    "softwareTerms",
    "npm",
    "node",
    "html",
    "typescript",
    "csharp",
    "scala",
    "fonts",
    "filetypes",
    "misc"
  ],
  "ignorePaths": [
    "**/*.spec.ts",
    "**/*.svg",
    "**/*/docs/**/*",
    ".vscode/**/*",
    "assets/**/*",
    "bun.lockb",
    "package.json",
    "pnpm-lock.yaml",
    "test/fixtures",
    "website/public/**/*",
    "THIRD-PARTY-LICENSE"
  ],
  "useGitignore": true,
  "words": [
    "bimap",
    "birecord",
    "clippy",
    "consequents",
    "declarators",
    "deepmerge",
    "dprint",
    "ESLR",
    "flexsearch",
    "greenlighted",
    "hatchpath",
    "Hoistable",
    "innerhtml",
    "knip",
    "linebreak",
    "lockb",
    "Mantine",
    "metas",
    "Monaspace",
    "Nextra",
    "Noto",
    "pathe",
    "pattycake",
    "preact",
    "prevs",
    "quasis",
    "rambda",
    "rehype",
    "ress",
    "rizzzse",
    "setstate",
    "shiki",
    "sonarjs",
    "Sukka",
    "tanstack",
    "tascript",
    "taze",
    "textnode",
    "textnodes",
    "todos",
    "treeshake",
    "TSES",
    "TSESAST",
    "tsup",
    "twoslash",
    "typeclass",
    "weakref"
  ]
}
